<?xml version="1.0" ?>
<xmcda:XMCDA xmlns:xmcda="http://www.decision-deck.org/2009/XMCDA-2.1.0" xmlns:xsi="http://www.w3.org/2001/XMLSchema-instance" xsi:schemaLocation="http://www.decision-deck.org/2009/XMCDA-2.1.0 http://www.decision-deck.org/xmcda/_downloads/XMCDA-2.1.0.xsd">
  <criteria>
    <criterion id="g1 - Price" name="Price">
      <scale>
        <quantitative>
          <preferenceDirection>max</preferenceDirection>
        </quantitative>
      </scale>
      <thresholds>
        <threshold mcdaConcept="indifference">
          <constant>
            <real>2</real>
          </constant>
        </threshold>
        <threshold mcdaConcept="preference">
          <constant>
            <real>10</real>
          </constant>
        </threshold>
        <threshold mcdaConcept="veto">
          <constant>
            <real>0</real>
          </constant>
        </threshold>
      </thresholds>
    </criterion>
    <criterion id="g2 - Location" name="Location">
      <scale>
        <quantitative>
          <preferenceDirection>max</preferenceDirection>
        </quantitative>
      </scale>
      <thresholds>
        <threshold mcdaConcept="indifference">
          <constant>
            <real>0</real>
          </constant>
        </threshold>
        <threshold mcdaConcept="preference">
          <constant>
            <real>1.9</real>
          </constant>
        </threshold>
        <threshold mcdaConcept="veto">
          <constant>
            <real>0</real>
          </constant>
        </threshold>
      </thresholds>
    </criterion>
    <criterion id="g3 - Schedule" name="Schedule">
      <scale>
        <quantitative>
          <preferenceDirection>min</preferenceDirection>
        </quantitative>
      </scale>
      <thresholds>
        <threshold mcdaConcept="indifference">
          <constant>
            <real>0</real>
          </constant>
        </threshold>
        <threshold mcdaConcept="preference">
          <constant>
            <real>2</real>
          </constant>
        </threshold>
        <threshold mcdaConcept="veto">
          <constant>
            <real>3.9</real>
          </constant>
        </threshold>
      </thresholds>
    </criterion>
    <criterion id="g4 - Parking" name="Parking">
      <scale>
        <quantitative>
          <preferenceDirection>max</preferenceDirection>
        </quantitative>
      </scale>
      <thresholds>
        <threshold mcdaConcept="indifference">
          <constant>
            <real>2.05</real>
          </constant>
        </threshold>
        <threshold mcdaConcept="preference">
          <constant>
            <real>5</real>
          </constant>
        </threshold>
        <threshold mcdaConcept="veto">
          <constant>
            <real>0</real>
          </constant>
        </threshold>
      </thresholds>
    </criterion>
    <criterion id="g5 - Culture" name="Culture">
      <scale>
        <quantitative>
          <preferenceDirection>max</preferenceDirection>
        </quantitative>
      </scale>
      <thresholds>
        <threshold mcdaConcept="indifference">
          <constant>
            <real>4</real>
          </constant>
        </threshold>
        <threshold mcdaConcept="preference">
          <constant>
            <real>3.4</real>
          </constant>
        </threshold>
        <threshold mcdaConcept="veto">
          <constant>
            <real>3.33</real>
          </constant>
        </threshold>
      </thresholds>
    </criterion>
    <criterion id="g6 - Menu Variety" name="Menu Variety">
      <scale>
        <quantitative>
          <preferenceDirection>max</preferenceDirection>
        </quantitative>
      </scale>
      <thresholds>
        <threshold mcdaConcept="indifference">
          <constant>
            <real>6</real>
          </constant>
        </threshold>
        <threshold mcdaConcept="preference">
          <constant>
            <real>6</real>
          </constant>
        </threshold>
        <threshold mcdaConcept="veto">
          <constant>
            <real>0</real>
          </constant>
        </threshold>
      </thresholds>
    </criterion>
  </criteria>
</xmcda:XMCDA>
